NPSO/__init__.py
NPSO/config.py
NPSO/_Particle/__init__.py
NPSO/_Particle/particle.py
NPSO/_Swarm/__init__.py
NPSO/_Swarm/swarm.py
NPSO-0.0.15.dist-info/LICENSE
NPSO-0.0.15.dist-info/METADATA
NPSO-0.0.15.dist-info/WHEEL
NPSO-0.0.15.dist-info/top_level.txt
NPSO-0.0.15.dist-info/RECORD
