Metadata-Version: 2.1
Name: NPSO
Version: 0.0.15
Summary: UNKNOWN
Home-page: https://github.com/zasexton/PyPso
Author: Zachary A. Sexton
Author-email: zsexton@stanford.edu
License: UNKNOWN
Download-URL: https://github.com/zasexton/PyPso
Platform: UNKNOWN
Classifier: Intended Audience :: Science/Research
Classifier: Programming Language :: Python :: 3.6
Classifier: Topic :: Scientific/Engineering
Classifier: Operating System :: MacOS
Requires-Dist: numpy (>=1.14.2)
Requires-Dist: sympy (>=1.1.1)
Requires-Dist: matplotlib (>=2.2.2)
